[
    {
        "vehicle_id": 1,
        "max_speed": 180,
        "brand": "BMW",
        "year": 2020,
        "color": "Red",
        "status": "available",
        "daily_rate": 100,
        "type_of_vehicle": "car",
        "time": "2024-10-08 18:25:37"
    },
    {
        "vehicle_id": 2,
        "max_speed": 250,
        "brand": "Scania",
        "year": 2022,
        "color": "Green",
        "status": "available",
        "daily_rate": 150,
        "type_of_vehicle": "truck",
        "time": "2024-10-08 18:25:37"
    },
    {
        "vehicle_id": 3,
        "max_speed": 200,
        "brand": "Yamaha",
        "year": 2021,
        "color": "Blue",
        "status": "available",
        "daily_rate": 50,
        "type_of_vehicle": "motorbike",
        "time": "2024-10-08 18:25:37"
    },
    {
        "vehicle_id": 5,
        "max_speed": 500,
        "brand": "ferrari",
        "year": 2024,
        "color": "red",
        "status": "available",
        "daily_rate": 300,
        "type_of_vehicle": "car",
        "time": "2024-10-08 18:25:37"
    }
]